django_coolify/__init__.py
django_coolify/apps.py
django_coolify/client.py
django_coolify/config.py
django_coolify/urls.py
django_coolify/utils.py
django_coolify/views.py
django_coolify/management/__init__.py
django_coolify/management/commands/__init__.py
django_coolify/management/commands/deploy.py
django_coolify/management/commands/generate_config.py
django_coolify/management/commands/set_domain.py
django_coolify/management/commands/setup_infra.py
django_coolify-0.1.5.dist-info/METADATA
django_coolify-0.1.5.dist-info/WHEEL
django_coolify-0.1.5.dist-info/RECORD
