Metadata-Version: 2.4
Name: django-coolify
Version: 0.1.5
Summary: Django integration for Coolify - easy deployment and management
Requires-Python: >=3.12
Requires-Dist: django>=4.2
Requires-Dist: gitpython>=3.1.0
Requires-Dist: requests>=2.25.0
Provides-Extra: dev
Requires-Dist: black>=23.0; extra == 'dev'
Requires-Dist: isort>=5.0; extra == 'dev'
Requires-Dist: pytest-django>=4.5.0; extra == 'dev'
Requires-Dist: pytest>=7.0; extra == 'dev'
